cruditor/__init__.py
cruditor/collection.py
cruditor/datastructures.py
cruditor/filters.py
cruditor/forms.py
cruditor/mixins.py
cruditor/views.py
cruditor/client/js/cruditor.js
cruditor/client/js/components/formset.js
cruditor/client/scss/_alerts.scss
cruditor/client/scss/_forms.scss
cruditor/client/scss/_login.scss
cruditor/client/scss/_views.scss
cruditor/client/scss/cruditor.scss
cruditor/locale/de/LC_MESSAGES/django.mo
cruditor/locale/de/LC_MESSAGES/django.po
cruditor/locale/fr/LC_MESSAGES/django.mo
cruditor/locale/fr/LC_MESSAGES/django.po
cruditor/static/cruditor/css/cruditor.css
cruditor/static/cruditor/css/cruditor.css.map
cruditor/static/cruditor/js/cruditor.js
cruditor/static/cruditor/js/cruditor.js.LICENSE.txt
cruditor/static/cruditor/js/cruditor.js.map
cruditor/templates/cruditor/403.html
cruditor/templates/cruditor/404.html
cruditor/templates/cruditor/base.html
cruditor/templates/cruditor/delete.html
cruditor/templates/cruditor/form.html
cruditor/templates/cruditor/list.html
cruditor/templates/cruditor/login.html
cruditor/templates/cruditor/logout.html
cruditor/templates/cruditor/forms/inline-formset.html
cruditor/templates/cruditor/includes/breadcrumb.html
cruditor/templates/cruditor/includes/extrahead.html
cruditor/templates/cruditor/includes/filter-form.html
cruditor/templates/cruditor/includes/menu.html
cruditor/templates/cruditor/includes/messages.html
cruditor/templates/cruditor/includes/navigation.html
cruditor/templates/cruditor/includes/table-pagination.html
cruditor/templates/cruditor/includes/table.html
cruditor/templates/cruditor/includes/titlebuttons.html
django_cruditor-3.1.0.dist-info/METADATA
django_cruditor-3.1.0.dist-info/WHEEL
django_cruditor-3.1.0.dist-info/top_level.txt
django_cruditor-3.1.0.dist-info/RECORD
