Metadata-Version: 2.2
Name: django-cruditor
Version: 3.1.0
Summary: A set of class based views and mixins to generate CRUD interfaces.
Author-email: Stephan Jaekel <steph@rdev.info>
Project-URL: Homepage, https://github.com/stephrdev/django-cruditor
Project-URL: Repository, https://github.com/stephrdev/django-cruditor
Project-URL: Documentation, https://django-cruditor.readthedocs.io
Classifier: Development Status :: 5 - Production/Stable
Classifier: License :: OSI Approved :: MIT License
Classifier: Environment :: Web Environment
Classifier: Framework :: Django
Classifier: Intended Audience :: Developers
Classifier: Operating System :: Unix
Classifier: Programming Language :: Python
Classifier: Programming Language :: Python :: 3
Requires-Python: <4,>=3.10
Requires-Dist: Django>=4.2
Requires-Dist: django-tapeforms>=2.2
Provides-Extra: tables
Requires-Dist: django-tables2>=2.6; extra == "tables"
Provides-Extra: filters
Requires-Dist: django-filter>=24.3; extra == "filters"
